codeforces_translate/__init__.py
codeforces_translate/cf_translate.py
codeforces_translate-0.1.2.dist-info/LICENSE
codeforces_translate-0.1.2.dist-info/METADATA
codeforces_translate-0.1.2.dist-info/WHEEL
codeforces_translate-0.1.2.dist-info/entry_points.txt
codeforces_translate-0.1.2.dist-info/top_level.txt
codeforces_translate-0.1.2.dist-info/RECORD
