Metadata-Version: 2.1
Name: codeforces-translate
Version: 0.1.2
Summary: codeforces 翻译
Home-page: https://github.com/therehello/codeforces-translate
Author: Therehello
Author-email: therehello@qq.com
Classifier: Programming Language :: Python :: 3
Classifier: License :: OSI Approved :: MIT License
Classifier: Operating System :: OS Independent
License-File: LICENSE
Requires-Dist: html2text
Requires-Dist: pygtrans
Requires-Dist: bs4
Requires-Dist: requests
Requires-Dist: lxml
